{"_ts":[1585703643,1585798612,1585858200],"_r":{"breakdown":{"html":{"bytes":[35729,24331,35746],"requests":[10,7,10]},"js":{"bytes":[361269,146366,361654],"requests":[34,26,34]},"css":{"bytes":[235198,111492,235198],"requests":[14,11,14]},"image":{"bytes":[788653,783452,703849],"requests":[48,45,49]},"flash":{"bytes":[0,0,0],"requests":[0,0,0]},"font":{"bytes":[146028,0,146028],"requests":[7,0,7]},"video":{"bytes":[0,0,0],"requests":[0,0,0]},"other":{"bytes":[4872,145117,4815],"requests":[1,17,1]}},"date":[1585703643,1585798612,1585858200],"domElements":[1178,null,1177],"domInteractive":[9260,0,9661],"firstPaint":[6691.9999999991,0,7133.2000000002],"fullyLoaded":[22749,62174,25515],"id":["200401_SR_b4c68d42c2c9f499c0ea514a3aab5a82","200402_4N_dc53cedbaae2f999ae9936ceee8c7206","200402_J0_b5973a1ea9dba94464b4af3a01697f46"],"loadTime":[18435,62174,19751],"render":[6702,0,7149],"SpeedIndex":[7396,0,8194],"TTFB":[2655,2733,3002],"videoFrames":[[{"_i":"ms_000000.jpg","_t":0,"_vc":0},{"_i":"ms_006702.jpg","_t":6702,"_vc":25},{"_i":"ms_006721.jpg","_t":6721,"_vc":26},{"_i":"ms_006744.jpg","_t":6744,"_vc":26},{"_i":"ms_006765.jpg","_t":6765,"_vc":26},{"_i":"ms_006783.jpg","_t":6783,"_vc":26},{"_i":"ms_006799.jpg","_t":6799,"_vc":26},{"_i":"ms_006839.jpg","_t":6839,"_vc":26},{"_i":"ms_006859.jpg","_t":6859,"_vc":26},{"_i":"ms_006877.jpg","_t":6877,"_vc":26},{"_i":"ms_006895.jpg","_t":6895,"_vc":26},{"_i":"ms_006916.jpg","_t":6916,"_vc":26},{"_i":"ms_006933.jpg","_t":6933,"_vc":26},{"_i":"ms_006950.jpg","_t":6950,"_vc":26},{"_i":"ms_006972.jpg","_t":6972,"_vc":26},{"_i":"ms_006990.jpg","_t":6990,"_vc":26},{"_i":"ms_007008.jpg","_t":7008,"_vc":26},{"_i":"ms_007026.jpg","_t":7026,"_vc":26},{"_i":"ms_007046.jpg","_t":7046,"_vc":25},{"_i":"ms_007062.jpg","_t":7062,"_vc":25},{"_i":"ms_007243.jpg","_t":7243,"_vc":25},{"_i":"ms_007395.jpg","_t":7395,"_vc":50},{"_i":"ms_007581.jpg","_t":7581,"_vc":92},{"_i":"ms_007818.jpg","_t":7818,"_vc":99},{"_i":"ms_014391.jpg","_t":14391,"_vc":100}],[{"_i":"ms_000000.jpg","_t":0,"_vc":100}],[{"_i":"ms_000000.jpg","_t":0,"_vc":0},{"_i":"ms_007149.jpg","_t":7149,"_vc":21},{"_i":"ms_007168.jpg","_t":7168,"_vc":22},{"_i":"ms_007190.jpg","_t":7190,"_vc":21},{"_i":"ms_007209.jpg","_t":7209,"_vc":21},{"_i":"ms_007232.jpg","_t":7232,"_vc":21},{"_i":"ms_007249.jpg","_t":7249,"_vc":21},{"_i":"ms_007269.jpg","_t":7269,"_vc":21},{"_i":"ms_007291.jpg","_t":7291,"_vc":21},{"_i":"ms_007310.jpg","_t":7310,"_vc":21},{"_i":"ms_007329.jpg","_t":7329,"_vc":21},{"_i":"ms_007348.jpg","_t":7348,"_vc":21},{"_i":"ms_007365.jpg","_t":7365,"_vc":21},{"_i":"ms_007514.jpg","_t":7514,"_vc":21},{"_i":"ms_007664.jpg","_t":7664,"_vc":21},{"_i":"ms_007732.jpg","_t":7732,"_vc":24},{"_i":"ms_008034.jpg","_t":8034,"_vc":24},{"_i":"ms_008419.jpg","_t":8419,"_vc":99},{"_i":"ms_014737.jpg","_t":14737,"_vc":100}]],"visualComplete":[14391,0,14737],"lighthouse":[30,null,30],"pagespeed":[82,81,80]}}