{"_ts":[1559367497],"_r":{"breakdown":{"html":{"bytes":[92519],"requests":[7]},"js":{"bytes":[327511],"requests":[19]},"css":{"bytes":[178025],"requests":[7]},"image":{"bytes":[272873],"requests":[12]},"flash":{"bytes":[0],"requests":[0]},"font":{"bytes":[143676],"requests":[7]},"video":{"bytes":[0],"requests":[0]},"other":{"bytes":[0],"requests":[0]}},"date":[1559367497],"domElements":[1115],"domInteractive":[6615],"firstPaint":[5863.7999999919],"fullyLoaded":[12919],"id":["190601_5G_6aa17a4178449eb82d40700bd25e07d2"],"loadTime":[12292],"render":[6038],"SpeedIndex":[9187],"TTFB":[2693],"videoFrames":[[{"_i":"ms_000000.jpg","_t":0,"_vc":0},{"_i":"ms_006038.jpg","_t":6038,"_vc":36},{"_i":"ms_006099.jpg","_t":6099,"_vc":35},{"_i":"ms_006233.jpg","_t":6233,"_vc":35},{"_i":"ms_006250.jpg","_t":6250,"_vc":35},{"_i":"ms_006268.jpg","_t":6268,"_vc":35},{"_i":"ms_006299.jpg","_t":6299,"_vc":35},{"_i":"ms_006319.jpg","_t":6319,"_vc":35},{"_i":"ms_006336.jpg","_t":6336,"_vc":35},{"_i":"ms_006354.jpg","_t":6354,"_vc":35},{"_i":"ms_006406.jpg","_t":6406,"_vc":35},{"_i":"ms_006512.jpg","_t":6512,"_vc":35},{"_i":"ms_007235.jpg","_t":7235,"_vc":57},{"_i":"ms_007418.jpg","_t":7418,"_vc":48},{"_i":"ms_007586.jpg","_t":7586,"_vc":48},{"_i":"ms_007852.jpg","_t":7852,"_vc":51},{"_i":"ms_007972.jpg","_t":7972,"_vc":51},{"_i":"ms_009194.jpg","_t":9194,"_vc":71},{"_i":"ms_009746.jpg","_t":9746,"_vc":73},{"_i":"ms_009858.jpg","_t":9858,"_vc":76},{"_i":"ms_011234.jpg","_t":11234,"_vc":76},{"_i":"ms_011448.jpg","_t":11448,"_vc":76},{"_i":"ms_012200.jpg","_t":12200,"_vc":76},{"_i":"ms_012300.jpg","_t":12300,"_vc":76},{"_i":"ms_012403.jpg","_t":12403,"_vc":76},{"_i":"ms_012507.jpg","_t":12507,"_vc":77},{"_i":"ms_012605.jpg","_t":12605,"_vc":76},{"_i":"ms_014792.jpg","_t":14792,"_vc":80},{"_i":"ms_014826.jpg","_t":14826,"_vc":82},{"_i":"ms_014910.jpg","_t":14910,"_vc":91},{"_i":"ms_015018.jpg","_t":15018,"_vc":96},{"_i":"ms_015107.jpg","_t":15107,"_vc":99},{"_i":"ms_015245.jpg","_t":15245,"_vc":100}]],"visualComplete":[15245],"lighthouse":[30],"pagespeed":[75]}}