{"_ts":[1561960437,1562048341,1562092493],"_r":{"breakdown":{"html":{"bytes":[87614,87626,87505],"requests":[7,8,8]},"js":{"bytes":[331828,331766,331766],"requests":[19,19,19]},"css":{"bytes":[182837,182837,182837],"requests":[8,8,8]},"image":{"bytes":[498509,540725,542160],"requests":[11,12,12]},"flash":{"bytes":[0,0,0],"requests":[0,0,0]},"font":{"bytes":[143676,143676,143676],"requests":[7,7,7]},"video":{"bytes":[0,0,0],"requests":[0,0,0]},"other":{"bytes":[0,0,0],"requests":[0,0,0]}},"date":[1561960437,1562048341,1562092493],"domElements":[1125,1125,1125],"domInteractive":[10307,7227,7919],"firstPaint":[9525.1999999964,6165.6999999977,6569.5999999989],"fullyLoaded":[30011,18593,22199],"id":["190701_ZT_2a088132003db0a208b8953dc9d3c481","190702_83_c2fb06671391f0abbff244a82655a1e9","190702_15_91754e96cca2ed46de8eb589825e8bdf"],"loadTime":[29180,17968,21546],"render":[9716,6334,6722],"SpeedIndex":[14505,8730,10967],"TTFB":[3116,2717,3326],"videoFrames":[[{"_i":"ms_000000.jpg","_t":0,"_vc":0},{"_i":"ms_009716.jpg","_t":9716,"_vc":42},{"_i":"ms_009802.jpg","_t":9802,"_vc":40},{"_i":"ms_009878.jpg","_t":9878,"_vc":40},{"_i":"ms_009897.jpg","_t":9897,"_vc":40},{"_i":"ms_009915.jpg","_t":9915,"_vc":40},{"_i":"ms_009934.jpg","_t":9934,"_vc":40},{"_i":"ms_009963.jpg","_t":9963,"_vc":40},{"_i":"ms_009996.jpg","_t":9996,"_vc":40},{"_i":"ms_010027.jpg","_t":10027,"_vc":40},{"_i":"ms_010112.jpg","_t":10112,"_vc":40},{"_i":"ms_010222.jpg","_t":10222,"_vc":40},{"_i":"ms_010776.jpg","_t":10776,"_vc":68},{"_i":"ms_010871.jpg","_t":10871,"_vc":53},{"_i":"ms_011089.jpg","_t":11089,"_vc":56},{"_i":"ms_012244.jpg","_t":12244,"_vc":56},{"_i":"ms_012953.jpg","_t":12953,"_vc":60},{"_i":"ms_013072.jpg","_t":13072,"_vc":60},{"_i":"ms_015127.jpg","_t":15127,"_vc":62},{"_i":"ms_016088.jpg","_t":16088,"_vc":79},{"_i":"ms_017052.jpg","_t":17052,"_vc":94},{"_i":"ms_017743.jpg","_t":17743,"_vc":94},{"_i":"ms_018016.jpg","_t":18016,"_vc":94},{"_i":"ms_018503.jpg","_t":18503,"_vc":93},{"_i":"ms_019398.jpg","_t":19398,"_vc":70},{"_i":"ms_019985.jpg","_t":19985,"_vc":71},{"_i":"ms_020495.jpg","_t":20495,"_vc":79},{"_i":"ms_020816.jpg","_t":20816,"_vc":79},{"_i":"ms_021014.jpg","_t":21014,"_vc":79},{"_i":"ms_021962.jpg","_t":21962,"_vc":94},{"_i":"ms_022772.jpg","_t":22772,"_vc":86},{"_i":"ms_023524.jpg","_t":23524,"_vc":86},{"_i":"ms_024003.jpg","_t":24003,"_vc":81},{"_i":"ms_026487.jpg","_t":26487,"_vc":85},{"_i":"ms_026515.jpg","_t":26515,"_vc":90},{"_i":"ms_027007.jpg","_t":27007,"_vc":93},{"_i":"ms_029828.jpg","_t":29828,"_vc":92},{"_i":"ms_030023.jpg","_t":30023,"_vc":92},{"_i":"ms_030315.jpg","_t":30315,"_vc":100}],[{"_i":"ms_000000.jpg","_t":0,"_vc":0},{"_i":"ms_006334.jpg","_t":6334,"_vc":37},{"_i":"ms_006396.jpg","_t":6396,"_vc":36},{"_i":"ms_006517.jpg","_t":6517,"_vc":36},{"_i":"ms_006535.jpg","_t":6535,"_vc":36},{"_i":"ms_006553.jpg","_t":6553,"_vc":35},{"_i":"ms_006571.jpg","_t":6571,"_vc":35},{"_i":"ms_006590.jpg","_t":6590,"_vc":35},{"_i":"ms_006609.jpg","_t":6609,"_vc":35},{"_i":"ms_006635.jpg","_t":6635,"_vc":35},{"_i":"ms_006711.jpg","_t":6711,"_vc":35},{"_i":"ms_006802.jpg","_t":6802,"_vc":35},{"_i":"ms_007891.jpg","_t":7891,"_vc":53},{"_i":"ms_008003.jpg","_t":8003,"_vc":52},{"_i":"ms_008516.jpg","_t":8516,"_vc":52},{"_i":"ms_009605.jpg","_t":9605,"_vc":88},{"_i":"ms_010452.jpg","_t":10452,"_vc":91},{"_i":"ms_011006.jpg","_t":11006,"_vc":92},{"_i":"ms_011139.jpg","_t":11139,"_vc":92},{"_i":"ms_011357.jpg","_t":11357,"_vc":92},{"_i":"ms_012012.jpg","_t":12012,"_vc":92},{"_i":"ms_012105.jpg","_t":12105,"_vc":92},{"_i":"ms_012216.jpg","_t":12216,"_vc":92},{"_i":"ms_012313.jpg","_t":12313,"_vc":92},{"_i":"ms_012414.jpg","_t":12414,"_vc":92},{"_i":"ms_015144.jpg","_t":15144,"_vc":92},{"_i":"ms_015217.jpg","_t":15217,"_vc":92},{"_i":"ms_015331.jpg","_t":15331,"_vc":92},{"_i":"ms_015412.jpg","_t":15412,"_vc":93},{"_i":"ms_015516.jpg","_t":15516,"_vc":99},{"_i":"ms_015601.jpg","_t":15601,"_vc":99},{"_i":"ms_015727.jpg","_t":15727,"_vc":99},{"_i":"ms_017809.jpg","_t":17809,"_vc":99},{"_i":"ms_017910.jpg","_t":17910,"_vc":99},{"_i":"ms_018043.jpg","_t":18043,"_vc":99},{"_i":"ms_018113.jpg","_t":18113,"_vc":99},{"_i":"ms_018216.jpg","_t":18216,"_vc":99},{"_i":"ms_020959.jpg","_t":20959,"_vc":100}],[{"_i":"ms_000000.jpg","_t":0,"_vc":0},{"_i":"ms_006722.jpg","_t":6722,"_vc":35},{"_i":"ms_006754.jpg","_t":6754,"_vc":34},{"_i":"ms_006916.jpg","_t":6916,"_vc":34},{"_i":"ms_006934.jpg","_t":6934,"_vc":34},{"_i":"ms_006953.jpg","_t":6953,"_vc":33},{"_i":"ms_006971.jpg","_t":6971,"_vc":33},{"_i":"ms_006991.jpg","_t":6991,"_vc":33},{"_i":"ms_007007.jpg","_t":7007,"_vc":33},{"_i":"ms_007026.jpg","_t":7026,"_vc":33},{"_i":"ms_007117.jpg","_t":7117,"_vc":33},{"_i":"ms_007207.jpg","_t":7207,"_vc":33},{"_i":"ms_007990.jpg","_t":7990,"_vc":33},{"_i":"ms_008010.jpg","_t":8010,"_vc":35},{"_i":"ms_008519.jpg","_t":8519,"_vc":46},{"_i":"ms_008610.jpg","_t":8610,"_vc":45},{"_i":"ms_009231.jpg","_t":9231,"_vc":45},{"_i":"ms_009602.jpg","_t":9602,"_vc":49},{"_i":"ms_010394.jpg","_t":10394,"_vc":50},{"_i":"ms_010943.jpg","_t":10943,"_vc":86},{"_i":"ms_012100.jpg","_t":12100,"_vc":86},{"_i":"ms_012282.jpg","_t":12282,"_vc":86},{"_i":"ms_012860.jpg","_t":12860,"_vc":86},{"_i":"ms_012918.jpg","_t":12918,"_vc":86},{"_i":"ms_013009.jpg","_t":13009,"_vc":86},{"_i":"ms_013103.jpg","_t":13103,"_vc":87},{"_i":"ms_013208.jpg","_t":13208,"_vc":86},{"_i":"ms_015983.jpg","_t":15983,"_vc":86},{"_i":"ms_016066.jpg","_t":16066,"_vc":86},{"_i":"ms_016247.jpg","_t":16247,"_vc":87},{"_i":"ms_016313.jpg","_t":16313,"_vc":88},{"_i":"ms_016412.jpg","_t":16412,"_vc":89},{"_i":"ms_018620.jpg","_t":18620,"_vc":89},{"_i":"ms_018712.jpg","_t":18712,"_vc":89},{"_i":"ms_018808.jpg","_t":18808,"_vc":88},{"_i":"ms_018904.jpg","_t":18904,"_vc":86},{"_i":"ms_019014.jpg","_t":19014,"_vc":86},{"_i":"ms_019103.jpg","_t":19103,"_vc":86},{"_i":"ms_021797.jpg","_t":21797,"_vc":86},{"_i":"ms_021819.jpg","_t":21819,"_vc":86},{"_i":"ms_021912.jpg","_t":21912,"_vc":86},{"_i":"ms_022005.jpg","_t":22005,"_vc":86},{"_i":"ms_022113.jpg","_t":22113,"_vc":86},{"_i":"ms_022212.jpg","_t":22212,"_vc":86},{"_i":"ms_024079.jpg","_t":24079,"_vc":87},{"_i":"ms_024100.jpg","_t":24100,"_vc":88},{"_i":"ms_024213.jpg","_t":24213,"_vc":97},{"_i":"ms_024300.jpg","_t":24300,"_vc":99},{"_i":"ms_024410.jpg","_t":24410,"_vc":100}]],"visualComplete":[30315,20959,24410],"lighthouse":[30,30,30],"pagespeed":[69,66,66]}}