{"_ts":[1535782780,1535826926],"_r":{"breakdown":{"html":{"bytes":[41726,50100],"requests":[4,5]},"js":{"bytes":[306533,336655],"requests":[18,20]},"css":{"bytes":[191961,191297],"requests":[8,7]},"image":{"bytes":[524961,546455],"requests":[9,14]},"flash":{"bytes":[0,0],"requests":[0,0]},"font":{"bytes":[143336,143335],"requests":[7,7]},"video":{"bytes":[0,0],"requests":[0,0]},"other":{"bytes":[285,0],"requests":[1,0]}},"date":[1535782780,1535826926],"domElements":[1080,1081],"domInteractive":[7606,6667],"firstPaint":[7282.5000000012,6316.9000000053],"fullyLoaded":[18325,18391],"id":["180901_TX_606ff37c7c854e1260fd584bf32b5dfc","180901_BC_36de4be4cfe37f6fc2747d39c98736cc"],"loadTime":[18308,18314],"render":[7431,6407],"SpeedIndex":[9925,9645],"TTFB":[4041,2712],"videoFrames":[[{"_i":"ms_000000.jpg","_t":0,"_vc":0},{"_i":"ms_007431.jpg","_t":7431,"_vc":49},{"_i":"ms_007496.jpg","_t":7496,"_vc":48},{"_i":"ms_007513.jpg","_t":7513,"_vc":48},{"_i":"ms_007630.jpg","_t":7630,"_vc":48},{"_i":"ms_007650.jpg","_t":7650,"_vc":48},{"_i":"ms_007669.jpg","_t":7669,"_vc":48},{"_i":"ms_007686.jpg","_t":7686,"_vc":48},{"_i":"ms_007705.jpg","_t":7705,"_vc":48},{"_i":"ms_007723.jpg","_t":7723,"_vc":48},{"_i":"ms_007812.jpg","_t":7812,"_vc":48},{"_i":"ms_007938.jpg","_t":7938,"_vc":48},{"_i":"ms_008134.jpg","_t":8134,"_vc":63},{"_i":"ms_008429.jpg","_t":8429,"_vc":61},{"_i":"ms_008825.jpg","_t":8825,"_vc":60},{"_i":"ms_009078.jpg","_t":9078,"_vc":65},{"_i":"ms_009465.jpg","_t":9465,"_vc":65},{"_i":"ms_010037.jpg","_t":10037,"_vc":77},{"_i":"ms_011030.jpg","_t":11030,"_vc":79},{"_i":"ms_011333.jpg","_t":11333,"_vc":76},{"_i":"ms_014738.jpg","_t":14738,"_vc":77},{"_i":"ms_014818.jpg","_t":14818,"_vc":77},{"_i":"ms_015734.jpg","_t":15734,"_vc":77},{"_i":"ms_015828.jpg","_t":15828,"_vc":89},{"_i":"ms_015929.jpg","_t":15929,"_vc":90},{"_i":"ms_016049.jpg","_t":16049,"_vc":92},{"_i":"ms_016385.jpg","_t":16385,"_vc":99},{"_i":"ms_017867.jpg","_t":17867,"_vc":99},{"_i":"ms_017918.jpg","_t":17918,"_vc":99},{"_i":"ms_018005.jpg","_t":18005,"_vc":99},{"_i":"ms_018111.jpg","_t":18111,"_vc":99},{"_i":"ms_018216.jpg","_t":18216,"_vc":99},{"_i":"ms_018308.jpg","_t":18308,"_vc":100},{"_i":"ms_018325.jpg","_t":18325,"_vc":100}],[{"_i":"ms_000000.jpg","_t":0,"_vc":0},{"_i":"ms_006407.jpg","_t":6407,"_vc":45},{"_i":"ms_006470.jpg","_t":6470,"_vc":44},{"_i":"ms_006488.jpg","_t":6488,"_vc":44},{"_i":"ms_006668.jpg","_t":6668,"_vc":44},{"_i":"ms_006687.jpg","_t":6687,"_vc":44},{"_i":"ms_006705.jpg","_t":6705,"_vc":44},{"_i":"ms_006723.jpg","_t":6723,"_vc":44},{"_i":"ms_006741.jpg","_t":6741,"_vc":44},{"_i":"ms_006758.jpg","_t":6758,"_vc":44},{"_i":"ms_006803.jpg","_t":6803,"_vc":44},{"_i":"ms_006904.jpg","_t":6904,"_vc":44},{"_i":"ms_007199.jpg","_t":7199,"_vc":58},{"_i":"ms_007448.jpg","_t":7448,"_vc":55},{"_i":"ms_007831.jpg","_t":7831,"_vc":56},{"_i":"ms_007994.jpg","_t":7994,"_vc":60},{"_i":"ms_008628.jpg","_t":8628,"_vc":59},{"_i":"ms_010563.jpg","_t":10563,"_vc":63},{"_i":"ms_011308.jpg","_t":11308,"_vc":76},{"_i":"ms_014507.jpg","_t":14507,"_vc":77},{"_i":"ms_014839.jpg","_t":14839,"_vc":78},{"_i":"ms_014905.jpg","_t":14905,"_vc":84},{"_i":"ms_015007.jpg","_t":15007,"_vc":83},{"_i":"ms_015123.jpg","_t":15123,"_vc":85},{"_i":"ms_016416.jpg","_t":16416,"_vc":92},{"_i":"ms_016658.jpg","_t":16658,"_vc":99},{"_i":"ms_016720.jpg","_t":16720,"_vc":99},{"_i":"ms_016802.jpg","_t":16802,"_vc":99},{"_i":"ms_016906.jpg","_t":16906,"_vc":99},{"_i":"ms_017029.jpg","_t":17029,"_vc":99},{"_i":"ms_017310.jpg","_t":17310,"_vc":99},{"_i":"ms_017411.jpg","_t":17411,"_vc":99},{"_i":"ms_017507.jpg","_t":17507,"_vc":99},{"_i":"ms_017600.jpg","_t":17600,"_vc":99},{"_i":"ms_017717.jpg","_t":17717,"_vc":99},{"_i":"ms_017825.jpg","_t":17825,"_vc":99},{"_i":"ms_017913.jpg","_t":17913,"_vc":99},{"_i":"ms_018021.jpg","_t":18021,"_vc":99},{"_i":"ms_018113.jpg","_t":18113,"_vc":99},{"_i":"ms_018208.jpg","_t":18208,"_vc":99},{"_i":"ms_018314.jpg","_t":18314,"_vc":100},{"_i":"ms_018391.jpg","_t":18391,"_vc":100}]],"visualComplete":[18308,18314],"lighthouse":[31,31],"pagespeed":[64,64]}}