{"_ts":[1546328257,1546372389],"_r":{"breakdown":{"html":{"bytes":[5737,5738],"requests":[3,3]},"js":{"bytes":[19778,19778],"requests":[2,2]},"css":{"bytes":[200674,200674],"requests":[13,13]},"image":{"bytes":[258304,258304],"requests":[4,4]},"flash":{"bytes":[0,0],"requests":[0,0]},"font":{"bytes":[9154,9154],"requests":[1,1]},"video":{"bytes":[0,0],"requests":[0,0]},"other":{"bytes":[0,0],"requests":[0,0]}},"date":[1546328257,1546372389],"domElements":[1208,1210],"domInteractive":[3765,3907],"firstPaint":[2029.5999999998,2348.1999999931],"fullyLoaded":[6640,7604],"id":["190101_ZE_fa12b33290ca122a393490a50c1d24ac","190101_99_47005ed3bd1de17504ee8bd22b667b4c"],"loadTime":[5499,6037],"render":[5452,5578],"SpeedIndex":[5472,5751],"TTFB":[2416,2892],"videoFrames":[[{"_i":"ms_000000.jpg","_t":0,"_vc":0},{"_i":"ms_005452.jpg","_t":5452,"_vc":57},{"_i":"ms_005499.jpg","_t":5499,"_vc":100},{"_i":"ms_005709.jpg","_t":5709,"_vc":100},{"_i":"ms_005728.jpg","_t":5728,"_vc":100},{"_i":"ms_005746.jpg","_t":5746,"_vc":100},{"_i":"ms_005766.jpg","_t":5766,"_vc":100},{"_i":"ms_005784.jpg","_t":5784,"_vc":100},{"_i":"ms_005801.jpg","_t":5801,"_vc":100},{"_i":"ms_005819.jpg","_t":5819,"_vc":100},{"_i":"ms_005837.jpg","_t":5837,"_vc":100},{"_i":"ms_005860.jpg","_t":5860,"_vc":100},{"_i":"ms_005877.jpg","_t":5877,"_vc":100},{"_i":"ms_005897.jpg","_t":5897,"_vc":100},{"_i":"ms_005913.jpg","_t":5913,"_vc":100},{"_i":"ms_005931.jpg","_t":5931,"_vc":100},{"_i":"ms_005949.jpg","_t":5949,"_vc":100},{"_i":"ms_005967.jpg","_t":5967,"_vc":100},{"_i":"ms_005985.jpg","_t":5985,"_vc":100},{"_i":"ms_006003.jpg","_t":6003,"_vc":100},{"_i":"ms_006640.jpg","_t":6640,"_vc":100}],[{"_i":"ms_000000.jpg","_t":0,"_vc":0},{"_i":"ms_005578.jpg","_t":5578,"_vc":12},{"_i":"ms_005640.jpg","_t":5640,"_vc":70},{"_i":"ms_005808.jpg","_t":5808,"_vc":70},{"_i":"ms_005828.jpg","_t":5828,"_vc":70},{"_i":"ms_005848.jpg","_t":5848,"_vc":70},{"_i":"ms_005865.jpg","_t":5865,"_vc":70},{"_i":"ms_005884.jpg","_t":5884,"_vc":70},{"_i":"ms_005903.jpg","_t":5903,"_vc":70},{"_i":"ms_005923.jpg","_t":5923,"_vc":70},{"_i":"ms_005946.jpg","_t":5946,"_vc":70},{"_i":"ms_005963.jpg","_t":5963,"_vc":70},{"_i":"ms_005983.jpg","_t":5983,"_vc":70},{"_i":"ms_006001.jpg","_t":6001,"_vc":70},{"_i":"ms_006019.jpg","_t":6019,"_vc":70},{"_i":"ms_006037.jpg","_t":6037,"_vc":100},{"_i":"ms_006059.jpg","_t":6059,"_vc":100},{"_i":"ms_006078.jpg","_t":6078,"_vc":100},{"_i":"ms_006095.jpg","_t":6095,"_vc":100},{"_i":"ms_006111.jpg","_t":6111,"_vc":100},{"_i":"ms_007604.jpg","_t":7604,"_vc":100}]],"visualComplete":[5499,6037],"lighthouse":[31,31],"pagespeed":[82,82]}}