{"_ts":[1530431052],"_r":{"breakdown":{"html":{"bytes":[338193],"requests":[56]},"js":{"bytes":[1207677],"requests":[74]},"css":{"bytes":[205295],"requests":[14]},"image":{"bytes":[709793],"requests":[132]},"flash":{"bytes":[0],"requests":[0]},"font":{"bytes":[166331],"requests":[11]},"video":{"bytes":[0],"requests":[0]},"other":{"bytes":[135493],"requests":[143]}},"date":[1530431052],"domElements":[849],"domInteractive":[4408],"firstPaint":[3592.6999999938],"fullyLoaded":[13342],"id":["180701_8P_d92884c684dfdb3104484f012ae1ecaa"],"loadTime":[10066],"render":[3600],"SpeedIndex":[4379],"TTFB":[1407],"videoFrames":[[{"_i":"ms_000000.jpg","_t":0,"_vc":0},{"_i":"ms_003600.jpg","_t":3600,"_vc":73},{"_i":"ms_003800.jpg","_t":3800,"_vc":79},{"_i":"ms_003900.jpg","_t":3900,"_vc":79},{"_i":"ms_004200.jpg","_t":4200,"_vc":79},{"_i":"ms_004500.jpg","_t":4500,"_vc":79},{"_i":"ms_004700.jpg","_t":4700,"_vc":79},{"_i":"ms_004800.jpg","_t":4800,"_vc":79},{"_i":"ms_005600.jpg","_t":5600,"_vc":79},{"_i":"ms_005700.jpg","_t":5700,"_vc":77},{"_i":"ms_005800.jpg","_t":5800,"_vc":79},{"_i":"ms_006200.jpg","_t":6200,"_vc":79},{"_i":"ms_006300.jpg","_t":6300,"_vc":79},{"_i":"ms_006400.jpg","_t":6400,"_vc":79},{"_i":"ms_006600.jpg","_t":6600,"_vc":79},{"_i":"ms_006800.jpg","_t":6800,"_vc":95},{"_i":"ms_007000.jpg","_t":7000,"_vc":95},{"_i":"ms_007200.jpg","_t":7200,"_vc":98},{"_i":"ms_007300.jpg","_t":7300,"_vc":98},{"_i":"ms_007600.jpg","_t":7600,"_vc":98},{"_i":"ms_007700.jpg","_t":7700,"_vc":96},{"_i":"ms_007800.jpg","_t":7800,"_vc":95},{"_i":"ms_008100.jpg","_t":8100,"_vc":98},{"_i":"ms_008300.jpg","_t":8300,"_vc":98},{"_i":"ms_008400.jpg","_t":8400,"_vc":98},{"_i":"ms_008600.jpg","_t":8600,"_vc":98},{"_i":"ms_008800.jpg","_t":8800,"_vc":98},{"_i":"ms_009100.jpg","_t":9100,"_vc":98},{"_i":"ms_009600.jpg","_t":9600,"_vc":98},{"_i":"ms_009700.jpg","_t":9700,"_vc":96},{"_i":"ms_009800.jpg","_t":9800,"_vc":98},{"_i":"ms_010100.jpg","_t":10100,"_vc":99},{"_i":"ms_010200.jpg","_t":10200,"_vc":99},{"_i":"ms_010300.jpg","_t":10300,"_vc":100}]],"visualComplete":[10300],"lighthouse":[31],"pagespeed":[66]}}